baku/__init__.py
baku/build.py
baku/cmdline.py
baku/consts.py
baku/document.py
baku/environment.py
baku/index.py
baku/markdown.py
baku/post.py
baku/rss.py
baku/templating.py
baku/upgrade.py
baku/utils.py
baku/templates/blog.cfg
baku/templates/dark.css
baku/templates/icon.ico
baku/templates/index.html
baku/templates/light.css
baku/templates/post.html
baku/templates/pygments.css
baku/templates/rss.xml
baku-1.2.0.dist-info/licenses/LICENSE
baku-1.2.0.dist-info/METADATA
baku-1.2.0.dist-info/WHEEL
baku-1.2.0.dist-info/entry_points.txt
baku-1.2.0.dist-info/top_level.txt
baku-1.2.0.dist-info/RECORD
