Metadata-Version: 2.4
Name: Baku
Version: 1.2.0
Summary: Simple, Markdown-based blogging engine
Home-page: http://github.com/vladris/baku/
Download-URL: http://pypi.python.org/pypi/baku
Author: Vlad Riscutia
Author-email: vladris@outlook.com
License: MIT
Platform: any
Classifier: Development Status :: 5 - Production/Stable
Classifier: Environment :: Console
Classifier: Environment :: Web Environment
Classifier: Intended Audience :: End Users/Desktop
Classifier: License :: OSI Approved :: MIT License
Classifier: Operating System :: OS Independent
Classifier: Programming Language :: Python
Classifier: Topic :: Communications
Classifier: Topic :: Internet
License-File: LICENSE
Requires-Dist: Pygments>=2.13.0
Requires-Dist: misaka>=2.1.1
Requires-Dist: pyquery>=1.4.3
Dynamic: author
Dynamic: author-email
Dynamic: classifier
Dynamic: description
Dynamic: download-url
Dynamic: home-page
Dynamic: license
Dynamic: license-file
Dynamic: platform
Dynamic: requires-dist
Dynamic: summary
